flpinspect/__init__.py
flpinspect/__main__.py
flpinspect/constants.py
flpinspect/gui_logger.py
flpinspect/inspector.py
flpinspect/treeview.py
flpinspect-0.1.0.dist-info/COPYING
flpinspect-0.1.0.dist-info/METADATA
flpinspect-0.1.0.dist-info/WHEEL
flpinspect-0.1.0.dist-info/entry_points.txt
flpinspect-0.1.0.dist-info/top_level.txt
flpinspect-0.1.0.dist-info/RECORD
