Metadata-Version: 2.1
Name: flpinspect
Version: 0.1.0
Summary: A GUI tool to inspect the structure of an FLP
Home-page: https://github.com/demberto/FLPInspect
Author: demberto
Author-email: demberto@protonmail.com
License: UNKNOWN
Project-URL: Source, https://github.com/demberto/FLPInspect
Project-URL: Documentation, https://flpinspect.rtfd.io
Project-URL: Changelog, https://github.com/demberto/FLPInspect/blob/master/CHANGELOG.md
Project-URL: Bug Tracker, https://github.com/demberto/FLPInspect/issues
Project-URL: TODO, https://github.com/demberto/FLPInspect/blob/master/TODO.md
Platform: UNKNOWN
Classifier: Programming Language :: Python :: 3 :: Only
Classifier: Programming Language :: Python :: 3.6
Classifier: Programming Language :: Python :: 3.7
Classifier: Programming Language :: Python :: 3.8
Classifier: Programming Language :: Python :: 3.9
Classifier: Programming Language :: Python :: 3.10
Classifier: License :: OSI Approved :: GNU General Public License v3 (GPLv3)
Classifier: Operating System :: OS Independent
Classifier: Development Status :: 3 - Alpha
Requires-Python: >=3.6
License-File: COPYING
Requires-Dist: pyflp (>=0.2.0)
